{
  "username": "ising52hz",
  "lookback_days": 90,
  "date_range": {
    "start": "2025-09-26",
    "end": "2025-12-25"
  },
  "scraped_at": "2025-12-25T16:20:28.710592",
  "total_videos": 34,
  "date_range_actual": {
    "earliest": "2025-09-28T19:09:08",
    "latest": "2025-12-24T20:25:37"
  },
  "total_stats": {
    "total_views": 21522000,
    "total_likes": 2205793,
    "total_comments": 13842,
    "total_shares": 77691
  },
  "average_stats": {
    "avg_views": 633000.0,
    "avg_likes": 64876.26470588235,
    "avg_comments": 407.11764705882354
  },
  "files": {
    "videos": "videos_raw_20251225_162028.json"
  },
  "scraper_stats": {
    "videos_scraped": 107,
    "profiles_scraped": 0,
    "errors": 0,
    "api_calls": 0
  }
}