{
  "feature_columns": [
    "views",
    "likes",
    "shares",
    "comments",
    "collects",
    "t_since_post",
    "like_rate",
    "share_rate",
    "comment_rate",
    "collect_rate",
    "views_velocity",
    "likes_velocity",
    "shares_velocity",
    "hour_of_day",
    "day_of_week"
  ],
  "sequence_length": 4,
  "target_horizons": [
    24
  ],
  "resample_interval": "none",
  "train_samples": 888,
  "val_samples": 173,
  "test_samples": 187,
  "created_at": "2025-12-27T14:51:34.788314"
}