{
  "username": "dieunhiofficial",
  "lookback_days": 90,
  "date_range": {
    "start": "2025-09-28",
    "end": "2025-12-27"
  },
  "scraped_at": "2025-12-27T02:11:05.946942",
  "total_videos": 40,
  "date_range_actual": {
    "earliest": "2025-09-28T18:42:35",
    "latest": "2025-12-26T20:00:58"
  },
  "total_stats": {
    "total_views": 51236500,
    "total_likes": 2593873,
    "total_comments": 15746,
    "total_shares": 173388
  },
  "average_stats": {
    "avg_views": 1280912.5,
    "avg_likes": 64846.825,
    "avg_comments": 393.65
  },
  "files": {
    "videos": "videos_raw_20251227_021105.json"
  },
  "scraper_stats": {
    "videos_scraped": 440,
    "profiles_scraped": 0,
    "errors": 0,
    "api_calls": 0
  }
}