{
  "username": "ising52hz",
  "lookback_days": 90,
  "date_range": {
    "start": "2025-09-27",
    "end": "2025-12-26"
  },
  "scraped_at": "2025-12-26T11:33:45.559559",
  "total_videos": 31,
  "date_range_actual": {
    "earliest": "2025-09-28T19:09:08",
    "latest": "2025-12-25T20:33:40"
  },
  "total_stats": {
    "total_views": 19320300,
    "total_likes": 1960785,
    "total_comments": 12657,
    "total_shares": 71293
  },
  "average_stats": {
    "avg_views": 623235.4838709678,
    "avg_likes": 63251.12903225807,
    "avg_comments": 408.2903225806452
  },
  "files": {
    "videos": "videos_raw_20251226_113345.json"
  },
  "scraper_stats": {
    "videos_scraped": 105,
    "profiles_scraped": 0,
    "errors": 0,
    "api_calls": 0
  }
}