{
  "username": "huynguyen.3101",
  "lookback_days": 90,
  "date_range": {
    "start": "2025-09-27",
    "end": "2025-12-26"
  },
  "scraped_at": "2025-12-26T22:39:34.273249",
  "total_videos": 28,
  "date_range_actual": {
    "earliest": "2025-10-01T22:51:39",
    "latest": "2025-12-20T18:54:07"
  },
  "total_stats": {
    "total_views": 17479200,
    "total_likes": 1051680,
    "total_comments": 16651,
    "total_shares": 55432
  },
  "average_stats": {
    "avg_views": 624257.1428571428,
    "avg_likes": 37560.0,
    "avg_comments": 594.6785714285714
  },
  "files": {
    "videos": "videos_raw_20251226_223934.json"
  },
  "scraper_stats": {
    "videos_scraped": 605,
    "profiles_scraped": 0,
    "errors": 0,
    "api_calls": 0
  }
}