{
  "username": "phuongnam.dv",
  "lookback_days": 180,
  "date_range": {
    "start": "2025-06-26",
    "end": "2025-12-23"
  },
  "scraped_at": "2025-12-23T23:54:28.494021",
  "total_videos": 38,
  "date_range_actual": {
    "earliest": "2025-08-01T10:20:15",
    "latest": "2025-12-18T09:16:00"
  },
  "total_stats": {
    "total_views": 85968900,
    "total_likes": 3954662,
    "total_comments": 26757,
    "total_shares": 226804
  },
  "average_stats": {
    "avg_views": 2262339.4736842103,
    "avg_likes": 104070.05263157895,
    "avg_comments": 704.1315789473684
  },
  "files": {
    "videos": "videos_raw_20251223_235428.json"
  },
  "scraper_stats": {
    "videos_scraped": 1337,
    "profiles_scraped": 0,
    "errors": 0,
    "api_calls": 0
  }
}