{
  "username": "hieuthuhai2222",
  "lookback_days": 90,
  "date_range": {
    "start": "2025-09-26",
    "end": "2025-12-25"
  },
  "scraped_at": "2025-12-25T17:08:10.631816",
  "total_videos": 5,
  "date_range_actual": {
    "earliest": "2025-11-23T11:03:20",
    "latest": "2025-12-24T07:59:37"
  },
  "total_stats": {
    "total_views": 4327000,
    "total_likes": 638000,
    "total_comments": 5812,
    "total_shares": 57178
  },
  "average_stats": {
    "avg_views": 865400.0,
    "avg_likes": 127600.0,
    "avg_comments": 1162.4
  },
  "files": {
    "videos": "videos_raw_20251225_170810.json"
  },
  "scraper_stats": {
    "videos_scraped": 473,
    "profiles_scraped": 0,
    "errors": 0,
    "api_calls": 0
  }
}