{
  "username": "ngthanhnhan2807",
  "lookback_days": 90,
  "date_range": {
    "start": "2025-09-27",
    "end": "2025-12-26"
  },
  "scraped_at": "2025-12-26T19:27:39.465723",
  "total_videos": 11,
  "date_range_actual": {
    "earliest": "2025-09-28T10:07:37",
    "latest": "2025-12-23T20:27:58"
  },
  "total_stats": {
    "total_views": 1687500,
    "total_likes": 61919,
    "total_comments": 937,
    "total_shares": 1505
  },
  "average_stats": {
    "avg_views": 153409.0909090909,
    "avg_likes": 5629.0,
    "avg_comments": 85.18181818181819
  },
  "files": {
    "videos": "videos_raw_20251226_192739.json"
  },
  "scraper_stats": {
    "videos_scraped": 655,
    "profiles_scraped": 0,
    "errors": 0,
    "api_calls": 0
  }
}