{
  "username": "ocean.gill",
  "lookback_days": 180,
  "date_range": {
    "start": "2025-06-27",
    "end": "2025-12-24"
  },
  "scraped_at": "2025-12-24T20:58:23.679665",
  "total_videos": 37,
  "date_range_actual": {
    "earliest": "2025-07-10T11:24:07",
    "latest": "2025-12-21T12:26:04"
  },
  "total_stats": {
    "total_views": 13180300,
    "total_likes": 1392212,
    "total_comments": 8493,
    "total_shares": 33276
  },
  "average_stats": {
    "avg_views": 356224.3243243243,
    "avg_likes": 37627.35135135135,
    "avg_comments": 229.54054054054055
  },
  "files": {
    "videos": "videos_raw_20251224_205823.json"
  },
  "scraper_stats": {
    "videos_scraped": 572,
    "profiles_scraped": 0,
    "errors": 0,
    "api_calls": 0
  }
}